xia_scw_forward/__init__.py
xia_scw_forward/forward.cpython-39-x86_64-linux-gnu.so
xia_scw_forward/templates/ScwForward/backend.tf
xia_scw_forward/templates/ScwForward/main.tf
xia_scw_forward/templates/ScwForward/output.tf
xia_scw_forward/templates/ScwForward/provider.tf
xia_scw_forward/templates/ScwForward/variables.tf
xia_scw_forward-0.0.3.dist-info/LICENSE.txt
xia_scw_forward-0.0.3.dist-info/METADATA
xia_scw_forward-0.0.3.dist-info/WHEEL
xia_scw_forward-0.0.3.dist-info/top_level.txt
xia_scw_forward-0.0.3.dist-info/RECORD
